{"v0pmYnyt4P6oNwGbX4rOkw==":"2%20-%20hotte-accueil-2-500x768.jpg","Om22Pr+VQo2hmSMaX3VI8g==":"fond-accueil-hotte-nettoyage-paris-1920x800.jpg","3R8kJTQV6Q25cD3siTpcJQ==":"image-13-950x635.png","h8jyH+UALIUDIoNZzcHliA==":"3%20-%20image-3-1351x1013.png","n3h+1g/OF47BFb692ULUnQ==":"image-11-1920x1080.png","9UWQI18wdoRxcrQ+oqHpAg==":"image-3-643x482.png","qaGUd3mO5d/oU6d98L4c+g==":"2%20-%20hotte-accueil-2-500x768.jpeg","Obp1OQZUh5dcZGZ6rlwNmA==":"fond-accueil-hotte-nettoyage-paris-643x268.jpeg","OFkSC32sdcH6C32Y8LSl4g==":"image-10-scaled-643x643.png","Ix4UXi6Z7dqXx+Nr/2r5dQ==":"7%20-%20logo-ventil-protect-hotte-80x48.jpg","K+p1Wb1wimrHetTN4GYwsA==":"logo%20expert-160x138.png","NQ4lRozdn1ANGrAGiO/3mw==":"i.webp","o1XaRaGuTA+6KHn8czHQZA==":"image-11-1351x760.png","Jfi7jlke/IAcrAj9K2ZW7Q==":"1-leroxy.jpg","dU/sdgbeZFsrldXZfVbBfA==":"2-mcdonalds.jpg","mpUXWcBSWF5ySumnymDrKw==":"3-kfc.jpg","JO7/jcos4woHlWxe6hi5mw==":"5-siemens.png","e3tjylZXLXHYSbCyG0QnZQ==":"6-ikea.jpg"}